ppdir/__init__.py
ppdir/attr_doc_string.py
ppdir/class_source_file.py
ppdir/display.py
ppdir/get_class_defines.py
ppdir/main.py
ppdir/merge.py
pretty_dir-0.9.13.dist-info/METADATA
pretty_dir-0.9.13.dist-info/WHEEL
pretty_dir-0.9.13.dist-info/RECORD
