Metadata-Version: 2.4
Name: pretty-dir
Version: 0.9.13
Summary: A pretty-printed version of dir(obj) for more comfortable debugging
Project-URL: Homepage, https://github.com/douglassimonsen/ppdir
Project-URL: Documentation, https://github.com/douglassimonsen/ppdir
Classifier: Development Status :: 4 - Beta
Classifier: Programming Language :: Python
Requires-Python: >=3.11.0
Requires-Dist: colorama>=0.4.6
Provides-Extra: dev
Requires-Dist: build>=1.2.2; extra == 'dev'
Requires-Dist: ruff>=0.12.7; extra == 'dev'
Provides-Extra: docs
Requires-Dist: mkdocs-material>=9.6.16; extra == 'docs'
Requires-Dist: mkdocs>=1.6.1; extra == 'docs'
Requires-Dist: mkdocstrings-python>=0.30.0; extra == 'docs'
